pointnet/__init__.py
pointnet/pointnet.py
pointnet/pointnet2.py
pointnet/taichi.py
pointnet/utils.py
pointnet-0.1.1.dist-info/LICENSE
pointnet-0.1.1.dist-info/METADATA
pointnet-0.1.1.dist-info/WHEEL
pointnet-0.1.1.dist-info/top_level.txt
pointnet-0.1.1.dist-info/RECORD
