Metadata-Version: 2.1
Name: pointnet
Version: 0.1.1
Summary: PointNet - Pytorch
Home-page: https://github.com/kentechx/pointnet
Author: Kaidi Shen
License: MIT
Keywords: 3D segmentation,3D classification,point cloud understanding
Classifier: Development Status :: 4 - Beta
Classifier: Intended Audience :: Developers
Classifier: Topic :: Scientific/Engineering :: Artificial Intelligence
Classifier: License :: OSI Approved :: MIT License
Classifier: Programming Language :: Python :: 3.6
License-File: LICENSE
Requires-Dist: torch (>=1.10)
Requires-Dist: einops (>=0.6.1)
Requires-Dist: taichi (>=1.6.0)
